MultiPropReg/LandmarksLoad_AS.py
MultiPropReg/convert_lablels.py
MultiPropReg/datagenerators.py
MultiPropReg/hyper_optimizer.py
MultiPropReg/mind.py
MultiPropReg/upperoptimizer.py
MultiPropReg/data/1yr_t1_atlas.nii
MultiPropReg/data/1yr_t1_atlas_seg.nii
MultiPropReg/data/__init__.py
MultiPropReg/data/atlas_seg_14labels.nii
MultiPropReg/data/atlas_vol.nii
MultiPropReg/models/__init__.py
MultiPropReg/models/pretrained_model_epoch200.ckpt
MultiPropReg/models/pretrained_model_epoch400.ckpt
MultiPropReg/pynd/__init__.py
MultiPropReg/pynd/imutils.py
MultiPropReg/pynd/ndutils.py
MultiPropReg/pynd/segutils.py
MultiPropReg/scripts/README.md
MultiPropReg/scripts/__init__.py
MultiPropReg/scripts/test.py
MultiPropReg/scripts/train_src_arcitecture.py
MultiPropReg/scripts/train_src_hyper.py
MultiPropReg/scripts/train_src_hyper_seg.py
MultiPropReg/torch/__init__.py
MultiPropReg/torch/architect_v5.py
MultiPropReg/torch/genotypes.py
MultiPropReg/torch/layers.py
MultiPropReg/torch/losses.py
MultiPropReg/torch/networks.py
MultiPropReg/torch/operations.py
MultiPropReg/torch/pipeline.png
MultiPropReg/torch/utils.py
MultiPropReg-0.1.1.dist-info/LICENSE
MultiPropReg-0.1.1.dist-info/METADATA
MultiPropReg-0.1.1.dist-info/WHEEL
MultiPropReg-0.1.1.dist-info/top_level.txt
MultiPropReg-0.1.1.dist-info/RECORD
