Metadata-Version: 2.1
Name: MultiPropReg
Version: 0.1.1
Summary: Image registration network using deformation field
Home-page: https://github.com/Co-Yonaka/MultiPropReg
License: MIT
Keywords: deformation,registration,imaging,mri
Classifier: Programming Language :: Python :: 3
Classifier: License :: OSI Approved :: MIT License
Classifier: Operating System :: OS Independent
Requires-Python: >=3.5.5
License-File: LICENSE
Requires-Dist: packaging
Requires-Dist: numpy
Requires-Dist: scipy
Requires-Dist: nibabel
